{
  "$schema": "https://json-schema.org/draft/2020-12/schema",
  "$id": "https://graphcaster.local/schemas/graph-document.schema.json",
  "title": "GraphCaster graph document (v1.5)",
  "type": "object",
  "additionalProperties": true,
  "required": ["schemaVersion", "nodes", "edges"],
  "properties": {
    "schemaVersion": {
      "type": "integer",
      "minimum": 1
    },
    "meta": {
      "type": "object",
      "additionalProperties": true,
      "properties": {
        "schemaVersion": { "type": "integer" },
        "graphId": { "type": "string", "minLength": 1 },
        "title": { "type": "string" },
        "author": { "type": "string" }
      }
    },
    "viewport": {
      "type": "object",
      "additionalProperties": true,
      "properties": {
        "x": { "type": "number" },
        "y": { "type": "number" },
        "zoom": { "type": "number" }
      }
    },
    "nodes": {
      "type": "array",
      "items": { "$ref": "#/$defs/node" }
    },
    "edges": {
      "type": "array",
      "items": { "$ref": "#/$defs/edge" }
    }
  },
  "$defs": {
    "gcPin": {
      "type": "object",
      "additionalProperties": true,
      "description": "Pinned task output (optional). When enabled and payload contains a dict processResult, the runner may skip spawning the process and use that result; otherwise payload seeds node_outputs before the visit merge.",
      "properties": {
        "enabled": { "type": "boolean" },
        "payload": {
          "type": "object",
          "additionalProperties": true,
          "description": "Merged into node_outputs[nodeId] before the step if context does not already define that id. Use shape compatible with run output, e.g. { \"processResult\": { \"success\": true, \"exitCode\": 0 } }."
        }
      }
    },
    "node": {
      "type": "object",
      "additionalProperties": false,
      "required": ["id", "type", "position", "data"],
      "properties": {
        "id": { "type": "string", "minLength": 1 },
        "type": {
          "type": "string",
          "minLength": 1,
          "description": "Known kinds: start, exit, task, graph_ref, comment, merge (join; data.mode passthrough | barrier), fork (fan-out; unconditional out_default edges only in runner). Other values: unknown executable (task-like handles in validation)."
        },
        "position": {
          "type": "object",
          "required": ["x", "y"],
          "properties": {
            "x": { "type": "number" },
            "y": { "type": "number" }
          },
          "additionalProperties": true
        },
        "data": {
          "type": "object",
          "additionalProperties": true,
          "description": "Node settings. Task nodes may include gcPin (see $defs.gcPin): n8n-style pinned output / pinData for dev reruns; runner merges payload into node_outputs unless that id is already set in --context-json. Task nodes may set stepCache: true to opt into cross-run disk step cache (F17) when the host passes --step-cache and --artifacts-base."
        },
        "parentId": {
          "type": "string",
          "minLength": 1,
          "description": "Optional id of a comment frame this node belongs to (editor-only grouping)."
        }
      }
    },
    "edge": {
      "type": "object",
      "additionalProperties": false,
      "required": ["id", "source", "target"],
      "properties": {
        "id": { "type": "string", "minLength": 1 },
        "source": { "type": "string", "minLength": 1 },
        "target": { "type": "string", "minLength": 1 },
        "sourceHandle": {
          "type": "string",
          "description": "Source handle id: out_default (success path) or out_error (failure path after task/graph_ref failure; Dify FAIL_BRANCH-style). See python/README.md."
        },
        "targetHandle": { "type": "string" },
        "source_handle": { "type": "string" },
        "target_handle": { "type": "string" },
        "condition": {
          "description": "Empty/null: unconditional. Max 65536 chars after trim. Literals true/false/1/0/yes/no. Mustache templates: {{dotted.path}} or {{dotted.path}} op literal (==, !=, <, <=, >, >=); first segment may be reserved $json (last_result snapshot, n8n-style). JSON object starting with { but not {{: JSON Logic subset (same predicate root). Other strings: truthiness of last_result. See python/README.md.",
          "oneOf": [{ "type": "null" }, { "type": "string" }]
        }
      }
    }
  }
}
